yfml/__init__.py
yfml/layers.py
yfml/quick_build.py
yfml/train.py
yfml/utils.py
yfml-0.1.0.dist-info/DESCRIPTION.rst
yfml-0.1.0.dist-info/METADATA
yfml-0.1.0.dist-info/RECORD
yfml-0.1.0.dist-info/WHEEL
yfml-0.1.0.dist-info/metadata.json
yfml-0.1.0.dist-info/top_level.txt
