Metadata-Version: 2.0
Name: yfml
Version: 0.1.0
Summary: based on tensorflow
Home-page: UNKNOWN
Author: yufan
Author-email: yufanzhou1993@gmail.com
License: MIT License
Platform: all
Requires-Dist: tensorflow
Requires-Dist: numpy
Requires-Dist: scipy
Requires-Dist: matplotlib
Requires-Dist: bleach (>=3.1.0)
